app/__init__.py
app/__main__.py
features/__init__.py
features/feature_computer.py
features/feature_extractor.py
features/kmer_processing.py
features/perceptual_hash_processing.py
features/substitution_processing.py
models/__init__.py
models/bad.pkl
models/bad_meta.pkl
models/bad_no_filter.pkl
models/get_model.py
prediction/__init__.py
prediction/predictor.py
utils/__init__.py
utils/utils.py
bad_phylo-0.1.0.dist-info/LICENSE
bad_phylo-0.1.0.dist-info/METADATA
bad_phylo-0.1.0.dist-info/WHEEL
bad_phylo-0.1.0.dist-info/entry_points.txt
bad_phylo-0.1.0.dist-info/top_level.txt
bad_phylo-0.1.0.dist-info/RECORD
