Metadata-Version: 2.1
Name: bad-phylo
Version: 0.1.0
Summary: Tool for the estimation of the difficulty of phylogenetic placements
Author: Julius Wiegert
Author-email: julius-wiegert@web.de
License-File: LICENSE
Requires-Dist: pandas
Requires-Dist: numpy
Requires-Dist: ete3
Requires-Dist: biopython
Requires-Dist: networkx
Requires-Dist: scipy
Requires-Dist: lightgbm ==4.1.0
Requires-Dist: shap
Requires-Dist: rich-argparse
Requires-Dist: pyprobables
Requires-Dist: matplotlib
